resamplelib/__init__.py
resamplelib/binning.py
resamplelib/jackknife.py
resamplelib-0.0.7.dist-info/LICENSE
resamplelib-0.0.7.dist-info/METADATA
resamplelib-0.0.7.dist-info/WHEEL
resamplelib-0.0.7.dist-info/top_level.txt
resamplelib-0.0.7.dist-info/RECORD
