Metadata-Version: 2.1
Name: resamplelib
Version: 0.0.7
Summary: Resampling methods
Home-page: https://github.com/ocabanas/resamplelib
Author: Oriol Cabanas
Author-email: oriol.cabanas@gmail.com
License: MIT
Keywords: binning jackknife
Platform: UNKNOWN
Classifier: Development Status :: 4 - Beta
Classifier: Intended Audience :: Developers
Classifier: Topic :: Internet
Classifier: License :: OSI Approved :: MIT License
Classifier: Programming Language :: Python
Classifier: Programming Language :: Python :: 3
Classifier: Programming Language :: Python :: 3.6
Requires-Dist: numpy
Requires-Dist: numba
Requires-Dist: matplotlib
Requires-Dist: scipy
